{"changelog_pro-design-admin.md":"B9CIEErc","changelog_pro-design-vue.md":"Zv3D_lAw","component_button.md":"Cpz3guTz","component_clipboard.md":"DjSKDgk4","component_config-provider.md":"BSAKk7Lq","component_counter.md":"pO1YScS0","component_design.md":"CI4j2tpJ","component_drawer.md":"CLzS289s","component_form.md":"BcKxJhdT","component_layout.md":"DZdCdav-","component_loading.md":"BNTGlbzW","component_modal-form.md":"DLfY0ClI","component_modal.md":"swrFFdcx","component_page.md":"Bs7QILCi","component_query-filter.md":"DXg84HSA","component_steps-form.md":"CXmg-sbI","component_table.md":"jErahnSH","guide_advanced_dark-mode.md":"ColeNTt1","guide_advanced_i18n.md":"Zt2XnAk8","guide_advanced_namespace.md":"f_hZvNAR","guide_advanced_theming.md":"D4raccXH","guide_development_build.md":"dl-a9rik","guide_development_custom-config.md":"dak7kP3f","guide_development_i18n.md":"CgE-Z6eN","guide_development_icon.md":"C5BVRTOL","guide_development_local.md":"DKsBr8HZ","guide_development_micro-app.md":"BJmX7qhm","guide_development_permission-control.md":"xfW-7zkB","guide_development_request-data.md":"CMPaQYGi","guide_development_router-menu.md":"CY2SHnHq","guide_development_rules.md":"CbQOObrw","guide_introduction_best-practices.md":"D0L5lD81","guide_introduction_quick-start.md":"bg0CETWX","guide_introduction_what-is.md":"CwINTiiS","index.md":"BM50JXIA"}
