{"changelog_pro-design-admin.md":"Cv8ICpHU","changelog_pro-design-vue.md":"7UvafFyf","component_button.md":"DhpTWtz-","component_clipboard.md":"BtEk0GL2","component_config-provider.md":"DRddBQiv","component_counter.md":"B9dfrxzO","component_design.md":"DoCBDo6-","component_drawer.md":"BPjMVK_V","component_form.md":"Cpme9jzF","component_layout.md":"CDLXFQrV","component_loading.md":"B1gbTHFX","component_modal-form.md":"Bim6bFOf","component_modal.md":"Bi68gNm5","component_page.md":"Lqv0g2at","component_query-filter.md":"yj7PtiQw","component_steps-form.md":"BC2gAyWf","component_table.md":"lMOJu71B","guide_advanced_dark-mode.md":"nLdqxq0N","guide_advanced_i18n.md":"qk7tTbWZ","guide_advanced_namespace.md":"B7OKYPxR","guide_advanced_theming.md":"B5R9WBPK","guide_development_build.md":"8pYSq8_I","guide_development_custom-config.md":"CZv_3Kbc","guide_development_i18n.md":"BsaT0_Mk","guide_development_icon.md":"BA7ewCqZ","guide_development_local.md":"Du13gPIW","guide_development_micro-app.md":"BoFfaY2Y","guide_development_permission-control.md":"Bcwo_PY6","guide_development_request-data.md":"Ck3vJWR2","guide_development_router-menu.md":"CKp2rX4N","guide_development_rules.md":"C7h5vKA2","guide_introduction_best-practices.md":"BEKZolFp","guide_introduction_quick-start.md":"CL6tUBe2","guide_introduction_what-is.md":"CHxNLaa8","index.md":"DP7akKrA"}
